LICENSE.txt
MANIFEST.in
README.rst
requirements.txt
setup.py
chai/__init__.py
chai/_termcolor.py
chai/chai.py
chai/comparators.py
chai/exception.py
chai/expectation.py
chai/mock.py
chai/python2.py
chai/spy.py
chai/stub.py
chai.egg-info/PKG-INFO
chai.egg-info/SOURCES.txt
chai.egg-info/dependency_links.txt
chai.egg-info/top_level.txt
examples/__init__.py
examples/__init__.pyc
examples/examples.py
examples/__pycache__/__init__.cpython-32.pyc
examples/__pycache__/examples.cpython-32.pyc
tests/__init__.py
tests/__init__.pyc
tests/chai_test.py
tests/chai_test.pyc
tests/comparator_py2.py
tests/comparator_py2.pyc
tests/comparator_test.py
tests/comparator_test.pyc
tests/expectation_test.py
tests/expectation_test.pyc
tests/functional_test.py
tests/functional_test.pyc
tests/mock_of_test.pyc
tests/mock_test.py
tests/mock_test.pyc
tests/sample_test.py
tests/sample_test.pyc
tests/samples.py
tests/samples.pyc
tests/stub_test.py
tests/stub_test.pyc
tests/__pycache__/__init__.cpython-32.pyc
tests/__pycache__/chai_test.cpython-32.pyc
tests/__pycache__/comparator_test.cpython-32.pyc
tests/__pycache__/expectation_test.cpython-32.pyc
tests/__pycache__/functional_test.cpython-32.pyc
tests/__pycache__/mock_test.cpython-32.pyc
tests/__pycache__/sample_test.cpython-32.pyc
tests/__pycache__/samples.cpython-32.pyc
tests/__pycache__/stub_test.cpython-32.pyc