Metadata-Version: 1.1
Name: chai
Version: 1.1.1
Summary: Easy to use mocking, stubbing and spying framework.
Home-page: https://github.com/agoragames/chai
Author: Vitaly Babiy, Aaron Westendorf
Author-email: vbabiy@agoragames.com, aaron@agoragames.com
License: LICENSE.txt
Keywords: python,test,mock
Platform: UNKNOWN
Classifier: Development Status :: 6 - Mature
Classifier: License :: OSI Approved :: BSD License
Classifier: Intended Audience :: Developers
Classifier: Operating System :: POSIX
Classifier: Topic :: Software Development :: Libraries
Classifier: Topic :: Software Development :: Libraries :: Python Modules
Classifier: Topic :: Software Development :: Testing
Classifier: Programming Language :: Python
Classifier: Programming Language :: Python :: 2.7
Classifier: Programming Language :: Python :: 3
Classifier: Programming Language :: Python :: 3.0
Classifier: Programming Language :: Python :: 3.1
Classifier: Programming Language :: Python :: 3.2
